hnccorr/__init__.py
hnccorr/base.py
hnccorr/example.py
hnccorr/graph.py
hnccorr/movie.py
hnccorr/postprocessor.py
hnccorr/seeds.py
hnccorr/segmentation.py
hnccorr/utils.py
hnccorr-2020.5.1.dist-info/LICENSE.md
hnccorr-2020.5.1.dist-info/METADATA
hnccorr-2020.5.1.dist-info/WHEEL
hnccorr-2020.5.1.dist-info/top_level.txt
hnccorr-2020.5.1.dist-info/RECORD
