Metadata-Version: 2.1
Name: hnccorr
Version: 2020.5.1
Summary: HNCcorr algorithm for cell detection in calcium-imaging.
Home-page: https://github.com/hochbaumGroup/HNCcorr
Author: Quico Spaen
Author-email: qspaen@berkeley.edu
License: Non-commercial license. Not an open-source license.
Keywords: Cell detection,Neuroscience,Calcium imaging
Platform: UNKNOWN
Classifier: Development Status :: 3 - Alpha
Classifier: Programming Language :: Python :: 3
Requires-Dist: closure-problem (>=2020.5.1)
Requires-Dist: networkx
Requires-Dist: numpy
Requires-Dist: pillow
Requires-Dist: six
Requires-Dist: sparsecomputation
Requires-Dist: scipy
Requires-Dist: tqdm
